"sideload__charliermarsh_bin_66679016e41b4d34e401777d/""charliermarsh.ruff-2024.26.0@win32-x64.vsix""; filename*=utf-8''charliermarsh.ruff-2024.26.0%40win32-x64.vsix"
sideload__charliermarsh_bin_66679016e41b4d34e401777d/__init__.py
sideload_charliermarsh_bin_66679016e41b4d34e401777d-1.0.0.dist-info/METADATA
sideload_charliermarsh_bin_66679016e41b4d34e401777d-1.0.0.dist-info/WHEEL
sideload_charliermarsh_bin_66679016e41b4d34e401777d-1.0.0.dist-info/top_level.txt
sideload_charliermarsh_bin_66679016e41b4d34e401777d-1.0.0.dist-info/RECORD
