Metadata-Version: 2.1
Name: sideload__charliermarsh_bin_66679016e41b4d34e401777d
Version: 1.0.0
Summary: Sideloaded package
Author: Null Void
Requires-Python: >=3.8
